zoomrlib/__init__.py
zoomrlib/__main__.py
zoomrlib/cli.py
zoomrlib/effect.py
zoomrlib/project.py
zoomrlib/utils.py
zoomrlib-1.1.0.dist-info/LICENSE
zoomrlib-1.1.0.dist-info/METADATA
zoomrlib-1.1.0.dist-info/WHEEL
zoomrlib-1.1.0.dist-info/entry_points.txt
zoomrlib-1.1.0.dist-info/RECORD
