Metadata-Version: 2.1
Name: zoomrlib
Version: 1.1.0
Summary: Library to read and write a ZoomR16 project file
Home-page: https://gitlab.com/remytms/zoomrlib
License: GPL-3.0-or-later
Keywords: zoomr16,audio,recorder
Author: Rémy Taymans
Author-email: remytms@tsmail.eu
Requires-Python: >=3.8,<4.0
Classifier: Development Status :: 5 - Production/Stable
Classifier: Intended Audience :: Developers
Classifier: License :: OSI Approved :: GNU General Public License v3 or later (GPLv3+)
Classifier: Operating System :: Microsoft :: Windows
Classifier: Operating System :: POSIX
Classifier: Operating System :: Unix
Classifier: Programming Language :: Python :: 3
Classifier: Programming Language :: Python :: 3.8
Classifier: Programming Language :: Python :: 3.9
Classifier: Programming Language :: Python :: 3.10
Classifier: Programming Language :: Python :: 3.11
Classifier: Programming Language :: Python :: 3.12
Classifier: Programming Language :: Python :: Implementation :: CPython
Classifier: Topic :: Multimedia :: Sound/Audio
Classifier: Topic :: Software Development :: Libraries
Project-URL: Repository, https://gitlab.com/remytms/zoomrlib
